[{"domain": "gxnnye.com", "expiry": 1524465069.852412, "httpOnly": true, "name": "qaqp_2132_saltkey", "path": "/", "secure": false, "value": "nDm55m55"}, {"domain": "gxnnye.com", "expiry": 1524465069.852552, "httpOnly": false, "name": "qaqp_2132_lastvisit", "path": "/", "secure": false, "value": "1521869477"}, {"domain": "gxnnye.com", "expiry": 1553409073, "httpOnly": false, "name": "_umdata", "path": "/", "secure": false, "value": "2BA477700510A7DF56E2C103C673A616B46EFDE986B121FBBCA9927BBB1B17A9A31038902C3D9225CD43AD3E795C914C98F9EE1DB9E29C266F29D68B26B6017A"}, {"domain": "gxnnye.com", "expiry": 1521959525.904798, "httpOnly": false, "name": "qaqp_2132_sid", "path": "/", "secure": false, "value": "nyzGg5"}, {"domain": "gxnnye.com", "expiry": 1537597927, "httpOnly": false, "name": "CNZZDATA1000328465", "path": "/", "secure": false, "value": "1917632768-1521871910-%7C1521871910"}, {"domain": "gxnnye.com", "expiry": 1521959469.852812, "httpOnly": false, "name": "qaqp_2132_pc_size_c", "path": "/", "secure": false, "value": "0"}, {"domain": "gxnnye.com", "expiry": 1837233071, "httpOnly": false, "name": "_uab_collina", "path": "/", "secure": false, "value": "152187307160816263301093"}, {"domain": "gxnnye.com", "expiry": 1521873370.960407, "httpOnly": false, "name": "qaqp_2132_sendmail", "path": "/", "secure": false, "value": "1"}, {"domain": ".gxnnye.com", "expiry": 1537597871, "httpOnly": false, "name": "UM_distinctid", "path": "/", "secure": false, "value": "16256b42f6fe0-0fea3965c9d832-3a614f0b-100200-16256b42f7028a"}, {"domain": "gxnnye.com", "httpOnly": false, "name": "qaqp_2132_secqaa", "path": "/", "secure": false, "value": "18176.80a4d091666ed3a3c6"}, {"domain": "gxnnye.com", "httpOnly": false, "name": "qaqp_2132_seccode", "path": "/", "secure": false, "value": "18177.cca11274441aeaa39a"}, {"domain": "gxnnye.com", "httpOnly": true, "name": "qaqp_2132_auth", "path": "/", "secure": false, "value": "37c1lo5IR3D2kHNLAzjFNaZ%2FOqwZc6rxR7HvvHf4atXvVwL0g73ORU1aP2GoA2Mv9OfMewSBK9XSglWnV5T5aK6mGw"}, {"domain": "gxnnye.com", "expiry": 1553409121.352584, "httpOnly": false, "name": "qaqp_2132_ulastactivity", "path": "/", "secure": false, "value": "3bd0kcN0AQyvkc636R883YCEWId%2B6KOwsB05eN5owudoiNmUlDti"}, {"domain": "gxnnye.com", "expiry": 1553409125.904503, "httpOnly": false, "name": "qaqp_2132_nofavfid", "path": "/", "secure": false, "value": "1"}, {"domain": "gxnnye.com", "expiry": 1521873425.904653, "httpOnly": false, "name": "qaqp_2132_onlineusernum", "path": "/", "secure": false, "value": "397"}, {"domain": "gxnnye.com", "expiry": 1521959526.850645, "httpOnly": false, "name": "qaqp_2132_lastact", "path": "/", "secure": false, "value": "1521873134%09home.php%09spacecp"}, {"domain": "gxnnye.com", "expiry": 1521873727, "httpOnly": false, "name": "qaqp_2132_noticeTitle", "path": "/", "secure": false, "value": "1"}]