[{"domain": "www.zsjsn.net", "httpOnly": true, "name": "aC0i_2132_secqaaSuiEl4C0", "path": "/", "secure": false, "value": "ea20NNxQC8O7lWHLpEZvXix74x4iLXMrOGyEWGpLbJlDg8jzQvpqqhELTLdGrHIBCv0SRTrBgQ64eCrzf1uV6xLFzOMNBbCAiZlHO6K8gWizuFgtOidZMpmt"}, {"domain": "www.zsjsn.net", "expiry": 1525341791.688333, "httpOnly": false, "name": "aC0i_2132_checkpm", "path": "/", "secure": false, "value": "1"}, {"domain": "www.zsjsn.net", "expiry": 1556877756.320068, "httpOnly": false, "name": "aC0i_2132_nofavfid", "path": "/", "secure": false, "value": "1"}, {"domain": "www.zsjsn.net", "expiry": 1527933710.107118, "httpOnly": true, "name": "aC0i_2132_saltkey", "path": "/", "secure": false, "value": "E0c0pJcO"}, {"domain": "www.zsjsn.net", "expiry": 1527933710.107221, "httpOnly": false, "name": "aC0i_2132_lastvisit", "path": "/", "secure": false, "value": "1525339133"}, {"domain": "www.zsjsn.net", "expiry": 1525342011.799, "httpOnly": false, "name": "aC0i_2132_sendmail", "path": "/", "secure": false, "value": "1"}, {"domain": "www.zsjsn.net", "httpOnly": false, "name": "__51cke__", "path": "/", "secure": false, "value": ""}, {"domain": "www.zsjsn.net", "httpOnly": true, "name": "aC0i_2132_seccodeSuiEl4C0", "path": "/", "secure": false, "value": "3c4ctB18GCix%2FRG%2F40uG5FgAwhclhFlwfU7LZJvCRh%2BehoDX%2BAG2aYiI2EiNx8lLN19HkGcmPlrJdq8jjFo"}, {"domain": "www.zsjsn.net", "expiry": 1525428156.320104, "httpOnly": false, "name": "aC0i_2132_sid", "path": "/", "secure": false, "value": "Bj5Pq6"}, {"domain": "www.zsjsn.net", "httpOnly": true, "name": "aC0i_2132_auth", "path": "/", "secure": false, "value": "4f56t8lk5JSD%2BBju%2BOY5twbYz9vHNotjzOUVN7B3Hqy94MOIDVKdZPNfxlbwFyCNwcwnMZWQ6tz1Sy5W18eFPm%2FgYqI"}, {"domain": "www.zsjsn.net", "expiry": 1556877742.061176, "httpOnly": false, "name": "aC0i_2132_ulastactivity", "path": "/", "secure": false, "value": "05a5zVSgPkjBtZBRKpLyIsWb3xQy0Zq0Pu%2BWUM3ZsKrrDIWBf7yl"}, {"domain": "www.zsjsn.net", "httpOnly": false, "name": "aC0i_2132_creditnotice", "path": "/", "secure": false, "value": "0D0D2D0D0D0D0D0D0D698629"}, {"domain": "www.zsjsn.net", "expiry": 1525342056.320085, "httpOnly": false, "name": "aC0i_2132_onlineusernum", "path": "/", "secure": false, "value": "144"}, {"domain": "www.zsjsn.net", "httpOnly": false, "name": "aC0i_2132_creditbase", "path": "/", "secure": false, "value": "0D0D0D0D0D0D0D0D0"}, {"domain": "www.zsjsn.net", "httpOnly": false, "name": "aC0i_2132_creditrule", "path": "/", "secure": false, "value": "%E6%AF%8F%E5%A4%A9%E7%99%BB%E5%BD%95"}, {"domain": "www.zsjsn.net", "httpOnly": false, "name": "__tins__18634411", "path": "/", "secure": false, "value": "%7B%22sid%22%3A%201525341713567%2C%20%22vd%22%3A%203%2C%20%22expires%22%3A%201525343561519%7D"}, {"domain": "www.zsjsn.net", "httpOnly": false, "name": "__51laig__", "path": "/", "secure": false, "value": "3"}, {"domain": "www.zsjsn.net", "expiry": 1525428161.68829, "httpOnly": false, "name": "aC0i_2132_lastact", "path": "/", "secure": false, "value": "1525342784%09home.php%09spacecp"}, {"domain": "www.zsjsn.net", "expiry": 1525342361, "httpOnly": false, "name": "aC0i_2132_noticeTitle", "path": "/", "secure": false, "value": "1"}]