[{"domain": ".tsdm.me", "expiry": 2147385600, "httpOnly": false, "name": "pgv_pvi", "path": "/", "secure": false, "value": "9170595456"}, {"domain": ".tsdm.me", "expiry": 1525772610.414508, "httpOnly": false, "name": "gkr8_8543_sendmail", "path": "/", "secure": false, "value": "1"}, {"domain": ".tsdm.me", "expiry": 1528364309.910521, "httpOnly": false, "name": "gkr8_8543_lastvisit", "path": "/", "secure": false, "value": "1525768701"}, {"domain": ".tsdm.me", "expiry": 1528364309.910422, "httpOnly": true, "name": "gkr8_8543_saltkey", "path": "/", "secure": false, "value": "iGVkU010"}, {"domain": ".tsdm.me", "httpOnly": false, "name": "pgv_info", "path": "/", "secure": false, "value": "ssi=s8068629735"}, {"domain": ".tsdm.me", "expiry": 1526377185.090204, "httpOnly": false, "name": "gkr8_8543_sina_bind_1735950", "path": "/", "secure": false, "value": "-1"}, {"domain": "www.tsdm.me", "httpOnly": false, "name": "__51cke__", "path": "/", "secure": false, "value": ""}, {"domain": ".tsdm.me", "httpOnly": true, "name": "gkr8_8543_secqaaS0bB71m0", "path": "/", "secure": false, "value": "7624ccQVFId%2FYSjluTDI3%2BGnlAJKYTxejIQFz0u3vdCkD2yc2GTteDYWm96IW0HMlslMwdeio3Lf609C4GYTqjBV9jM8h0cY48wmld9XHef5PStbFaYGoXBE"}, {"domain": ".tsdm.me", "httpOnly": true, "name": "gkr8_8543_seccodeS0bB71m0", "path": "/", "secure": false, "value": "cdb5uUTxssH1ckTRvHFMogyxg7PhtXL1UnTDqpNHYjeHGdw%2BbBOab0DvZ7RSztf3jkTMSugu7pO0Evuro%2Bw"}, {"domain": ".tsdm.me", "httpOnly": true, "name": "gkr8_8543_auth", "path": "/", "secure": false, "value": "fc1cHdkDk4YoIFYIWfczIVMnKJO5qbJTGA1TlZPbDSZCOwL3QH%2BUAUQkqOSjfqJEMFYFCczvEkeQZ7YkY26xtLeIi0xS"}, {"domain": ".tsdm.me", "expiry": 1525858788.32514, "httpOnly": false, "name": "gkr8_8543_sid", "path": "/", "secure": false, "value": "QxZzJs"}, {"domain": ".tsdm.me", "expiry": 1557308388.325105, "httpOnly": false, "name": "gkr8_8543_ulastactivity", "path": "/", "secure": false, "value": "a96deXHpUtDlDcPqTQtPz3CRJ9vwGGebt9lWZ7pqcKSjqNgdqOCd"}, {"domain": "www.tsdm.me", "httpOnly": false, "name": "__tins__5183328", "path": "/", "secure": false, "value": "%7B%22sid%22%3A%201525772311571%2C%20%22vd%22%3A%203%2C%20%22expires%22%3A%201525774188356%7D"}, {"domain": "www.tsdm.me", "httpOnly": false, "name": "__51laig__", "path": "/", "secure": false, "value": "3"}, {"domain": ".tsdm.me", "expiry": 1525858788.561717, "httpOnly": false, "name": "gkr8_8543_lastact", "path": "/", "secure": false, "value": "1525772380%09home.php%09spacecp"}, {"domain": ".tsdm.me", "expiry": 1557308388.56183, "httpOnly": false, "name": "gkr8_8543_connect_is_bind", "path": "/", "secure": false, "value": "0"}, {"domain": ".tsdm.me", "expiry": 1525772418.561897, "httpOnly": false, "name": "gkr8_8543_checkpm", "path": "/", "secure": false, "value": "1"}, {"domain": ".tsdm.me", "expiry": 1525772988, "httpOnly": false, "name": "gkr8_8543_noticeTitle", "path": "/", "secure": false, "value": "1"}]