[{"domain": ".kplsc.com", "expiry": 1555397815.041573, "httpOnly": true, "name": "__cfduid", "path": "/", "secure": false, "value": "d1f6371b397bcad1a0dff5211d46d77481523861809"}, {"domain": "www.kplsc.com", "expiry": 1523862115.544887, "httpOnly": false, "name": "Rl17_2132_sendmail", "path": "/", "secure": false, "value": "1"}, {"domain": "www.kplsc.com", "httpOnly": false, "name": "__51cke__", "path": "/", "secure": false, "value": ""}, {"domain": "www.kplsc.com", "expiry": 1526453815.04191, "httpOnly": false, "name": "Rl17_2132_lastvisit", "path": "/", "secure": false, "value": "1523858209"}, {"domain": "www.kplsc.com", "expiry": 1526453815.041794, "httpOnly": true, "name": "Rl17_2132_saltkey", "path": "/", "secure": false, "value": "GR00Kf0n"}, {"domain": "www.kplsc.com", "expiry": 1523948237.314797, "httpOnly": false, "name": "Rl17_2132_sid", "path": "/", "secure": false, "value": "adPNfD"}, {"domain": "www.kplsc.com", "httpOnly": false, "name": "__tins__19426079", "path": "/", "secure": false, "value": "%7B%22sid%22%3A%201523861816062%2C%20%22vd%22%3A%201%2C%20%22expires%22%3A%201523863616062%7D"}, {"domain": "www.kplsc.com", "httpOnly": false, "name": "Rl17_2132_seccode", "path": "/", "secure": false, "value": "109.cd22c9b162131f3fbb"}, {"domain": "www.kplsc.com", "httpOnly": false, "name": "__51laig__", "path": "/", "secure": false, "value": "1"}, {"domain": "www.kplsc.com", "httpOnly": true, "name": "Rl17_2132_auth", "path": "/", "secure": false, "value": "9beeegUYAKk8uWK0wT556V9tVLm%2Fak%2FZXvxldeSz04XoD5lEEG%2B8iHsv%2BNQDK3BwSNr571taJMdGjBH7Zky2ZZSQ"}, {"domain": "www.kplsc.com", "expiry": 1523948237.314691, "httpOnly": false, "name": "Rl17_2132_lastact", "path": "/", "secure": false, "value": "1523861831%09member.php%09logging"}, {"domain": "www.kplsc.com", "expiry": 1555397837.314741, "httpOnly": false, "name": "Rl17_2132_ulastactivity", "path": "/", "secure": false, "value": "214dhJuvOtVn55%2BySlguwHyWfxHLMwcXybKRC%2BpEL%2Bf3Vc9Cemus"}, {"domain": "www.kplsc.com", "expiry": 1555397837.315022, "httpOnly": false, "name": "Rl17_2132_lastcheckfeed", "path": "/", "secure": false, "value": "1772%7C1523861831"}, {"domain": "www.kplsc.com", "expiry": 1523861867.315081, "httpOnly": false, "name": "Rl17_2132_checkfollow", "path": "/", "secure": false, "value": "1"}, {"domain": "www.kplsc.com", "httpOnly": false, "name": "Rl17_2132_lip", "path": "/", "secure": false, "value": "113.67.73.56%2C1523861768"}]