[{"domain": "www.haoyongla.com", "expiry": 1522122330.73648, "httpOnly": false, "name": "zeL5_2132_sendmail", "path": "/", "secure": false, "value": "1"}, {"domain": "www.haoyongla.com", "expiry": 1524714030.616459, "httpOnly": false, "name": "zeL5_2132_lastvisit", "path": "/", "secure": false, "value": "1522118430"}, {"domain": "www.haoyongla.com", "expiry": 1524714030.616388, "httpOnly": true, "name": "zeL5_2132_saltkey", "path": "/", "secure": false, "value": "nNZm4zzx"}, {"domain": "www.haoyongla.com", "expiry": 1553658084.114951, "httpOnly": false, "name": "zeL5_2132_lastcheckfeed", "path": "/", "secure": false, "value": "10%7C1522122083"}, {"domain": "www.haoyongla.com", "expiry": 1522208484.114518, "httpOnly": false, "name": "zeL5_2132_lastact", "path": "/", "secure": false, "value": "1522122083%09member.php%09logging"}, {"domain": "www.haoyongla.com", "httpOnly": true, "name": "zeL5_2132_auth", "path": "/", "secure": false, "value": "879ekx%2B1cRcFu%2FyX5e7fFunkduHLhe4U7n8Yo1ctM9jTjfQqiTnw%2FzK0DCip4C%2Bf49Vqe%2FHpMF8T3Nb%2BrImAbg"}, {"domain": "www.haoyongla.com", "expiry": 1522208484.114621, "httpOnly": false, "name": "zeL5_2132_sid", "path": "/", "secure": false, "value": "wzAWGO"}, {"domain": "www.haoyongla.com", "httpOnly": false, "name": "zeL5_2132_seccode", "path": "/", "secure": false, "value": "1.4820062b37f9bae260"}, {"domain": "www.haoyongla.com", "expiry": 1553658084.114685, "httpOnly": false, "name": "zeL5_2132_ulastactivity", "path": "/", "secure": false, "value": "f0f3odljgF6JxaQ042sFb3C0JvI6mZGTg6XwTJBHjXFySr5pajl7"}, {"domain": "www.haoyongla.com", "expiry": 1522122114.114998, "httpOnly": false, "name": "zeL5_2132_checkfollow", "path": "/", "secure": false, "value": "1"}, {"domain": "www.haoyongla.com", "httpOnly": false, "name": "zeL5_2132_lip", "path": "/", "secure": false, "value": "113.67.19.178%2C1522089522"}]