[{"domain": "www.5ikantu.com", "expiry": 1524627972.365638, "httpOnly": true, "name": "Nhu8_2132_saltkey", "path": "/", "secure": true, "value": "jXkV77bX"}, {"domain": ".5ikantu.com", "expiry": 1537760773, "httpOnly": false, "name": "UM_distinctid", "path": "/", "secure": false, "value": "1626069dd41492-0b1c0c8036e589-3a614f0b-100200-1626069dd42cd"}, {"domain": "www.5ikantu.com", "expiry": 1524627972.365787, "httpOnly": false, "name": "Nhu8_2132_lastvisit", "path": "/", "secure": true, "value": "1522032359"}, {"domain": "www.5ikantu.com", "expiry": 1522036273.075039, "httpOnly": false, "name": "Nhu8_2132_sendmail", "path": "/", "secure": true, "value": "1"}, {"domain": "www.5ikantu.com", "expiry": 1553571995.984913, "httpOnly": false, "name": "Nhu8_2132_ulastactivity", "path": "/", "secure": true, "value": "1522035982%7C0"}, {"domain": "www.5ikantu.com", "httpOnly": true, "name": "Nhu8_2132_auth", "path": "/", "secure": true, "value": "e203ElFu0vNwn%2BSgtxuQWgqFwkqPWYc3UHLvL4Ka5JHZsGZXGPhy2pC1ASZeWDGfeIkSJkX22gOlCebzBVdCHoo"}, {"domain": ".5ikantu.com", "expiry": 1553571999, "httpOnly": false, "name": "Hm_lvt_b5a938a19c7d3ce8da310a4c7fb1b90d", "path": "/", "secure": false, "value": "1522035973"}, {"domain": "www.5ikantu.com", "expiry": 1537760799, "httpOnly": false, "name": "CNZZDATA1261594029", "path": "/", "secure": false, "value": "1374614322-1522035518-%7C1522035518"}, {"domain": "www.5ikantu.com", "httpOnly": false, "name": "Nhu8_2132_seccode", "path": "/", "secure": true, "value": "47.9d54a15557c52acb32"}, {"domain": "www.5ikantu.com", "httpOnly": false, "name": "Nhu8_2132_creditnotice", "path": "/", "secure": true, "value": "0D1D2D0D0D0D0D0D0D193"}, {"domain": "www.5ikantu.com", "httpOnly": false, "name": "Nhu8_2132_creditbase", "path": "/", "secure": true, "value": "0D0D0D0D0D0D0D0D0"}, {"domain": "www.5ikantu.com", "httpOnly": false, "name": "Nhu8_2132_creditrule", "path": "/", "secure": true, "value": "%E6%AF%8F%E5%A4%A9%E7%99%BB%E5%BD%95"}, {"domain": "www.5ikantu.com", "expiry": 1553571999.210046, "httpOnly": false, "name": "Nhu8_2132_nofavfid", "path": "/", "secure": true, "value": "1"}, {"domain": "www.5ikantu.com", "expiry": 1522036029.451433, "httpOnly": false, "name": "Nhu8_2132_checkpm", "path": "/", "secure": true, "value": "1"}, {"domain": ".5ikantu.com", "httpOnly": false, "name": "Hm_lpvt_b5a938a19c7d3ce8da310a4c7fb1b90d", "path": "/", "secure": false, "value": "1522035999"}, {"domain": "www.5ikantu.com", "expiry": 1522036599, "httpOnly": false, "name": "Nhu8_2132_noticeTitle", "path": "/", "secure": false, "value": "1"}, {"domain": "www.5ikantu.com", "expiry": 1522122402.16763, "httpOnly": false, "name": "Nhu8_2132_lastact", "path": "/", "secure": true, "value": "1522035989%09forum.php%09image"}]