[{"domain": "www.kishd.org", "expiry": 1528519144.17356, "httpOnly": true, "name": "F0Au_2132_saltkey", "path": "/", "secure": false, "value": "xCTo1Wbu"}, {"domain": "www.kishd.org", "expiry": 1525927444.54572, "httpOnly": false, "name": "F0Au_2132_sendmail", "path": "/", "secure": false, "value": "1"}, {"domain": "www.kishd.org", "expiry": 1525970403.535692, "httpOnly": false, "name": "F0Au_2132_security_cookiereport", "path": "/", "secure": false, "value": "f68ePLI2tL8TVCavagb%2Bmg1tyoL33q1awl%2BWaxRJpIZTEFhLOaQq"}, {"domain": ".kishd.org", "expiry": 1541651944, "httpOnly": false, "name": "UM_distinctid", "path": "/", "secure": false, "value": "16348586c45a3a-0372271636148e-3961430f-1fa400-16348586c4679a"}, {"domain": "www.kishd.org", "expiry": 1528519144.173604, "httpOnly": false, "name": "F0Au_2132_lastvisit", "path": "/", "secure": false, "value": "1525923544"}, {"domain": "www.kishd.org", "expiry": 1541652003, "httpOnly": false, "name": "CNZZDATA713434", "path": "/", "secure": false, "value": "cnzz_eid%3D1253390431-1525925012-%26ntime%3D1525925012"}, {"domain": "www.kishd.org", "httpOnly": true, "name": "F0Au_2132_auth", "path": "/", "secure": false, "value": "380bSLhkLRfl0meNqWeUcPisLfUGt9v8ELAbvLw0xEpwOZMlEsEMORyX%2BIfObZxdMHol7RV%2Frs4UL1B5ezVt06mKyW4"}, {"domain": "www.kishd.org", "httpOnly": false, "name": "F0Au_2132_lastsubset", "path": "/", "secure": false, "value": "2"}, {"domain": "www.kishd.org", "httpOnly": false, "name": "F0Au_2132_seccode", "path": "/", "secure": false, "value": "190.0f8b858577bd047468"}, {"domain": "www.kishd.org", "expiry": 1526013603.535627, "httpOnly": false, "name": "F0Au_2132_lastact", "path": "/", "secure": false, "value": "1525927204%09home.php%09spacecp"}, {"domain": "www.kishd.org", "httpOnly": false, "name": "F0Au_2132_secqaa", "path": "/", "secure": false, "value": "189.d9aa0e04fe25371a73"}, {"domain": "www.kishd.org", "expiry": 1557463199.664745, "httpOnly": false, "name": "F0Au_2132_ulastactivity", "path": "/", "secure": false, "value": "9f36zmvY1m7cZ875SKoy6EZ10HcKgoDhfn418hylh%2FqEo9SQaFdf"}, {"domain": "www.kishd.org", "httpOnly": false, "name": "F0Au_2132_creditnotice", "path": "/", "secure": false, "value": "0D0D2D0D0D0D0D0D0D116259"}, {"domain": "www.kishd.org", "httpOnly": false, "name": "F0Au_2132_creditbase", "path": "/", "secure": false, "value": "0D0D0D0D0D0D0D0D0"}, {"domain": "www.kishd.org", "httpOnly": false, "name": "F0Au_2132_creditrule", "path": "/", "secure": false, "value": "%E6%AF%8F%E5%A4%A9%E7%99%BB%E5%BD%95"}, {"domain": "www.kishd.org", "expiry": 1526013603.517858, "httpOnly": false, "name": "F0Au_2132_sid", "path": "/", "secure": false, "value": "v4kFF4"}, {"domain": "www.kishd.org", "httpOnly": false, "name": "F0Au_2132_lip", "path": "/", "secure": false, "value": "183.54.192.138%2C1525927193"}, {"domain": "www.kishd.org", "expiry": 1557463203.535665, "httpOnly": false, "name": "F0Au_2132_connect_is_bind", "path": "/", "secure": false, "value": "0"}, {"domain": "www.kishd.org", "expiry": 1557463203.517983, "httpOnly": false, "name": "F0Au_2132_lastcheckfeed", "path": "/", "secure": false, "value": "116259%7C1525927204"}, {"domain": "www.kishd.org", "expiry": 1525927233.517999, "httpOnly": false, "name": "F0Au_2132_checkfollow", "path": "/", "secure": false, "value": "1"}, {"domain": "www.kishd.org", "expiry": 1525927233.535716, "httpOnly": false, "name": "F0Au_2132_checkpm", "path": "/", "secure": false, "value": "1"}, {"domain": "www.kishd.org", "expiry": 1525927804, "httpOnly": false, "name": "F0Au_2132_noticeTitle", "path": "/", "secure": false, "value": "1"}]