[{"domain": "www.avhd2.com", "expiry": 1528453141.501062, "httpOnly": true, "name": "Hvgv_2132_saltkey", "path": "/", "secure": false, "value": "u0WGPteK"}, {"domain": "www.avhd2.com", "expiry": 1528453141.501163, "httpOnly": false, "name": "Hvgv_2132_lastvisit", "path": "/", "secure": false, "value": "1525857456"}, {"domain": ".avhd2.com", "expiry": 1541585943, "httpOnly": false, "name": "UM_distinctid", "path": "/", "secure": false, "value": "163446952d5737-09d5966f59d3ed-3961430f-1fa400-163446952d7993"}, {"domain": "www.avhd2.com", "httpOnly": true, "name": "Hvgv_2132_auth", "path": "/", "secure": false, "value": "3c9b%2BbDfzsn1shFH%2F59VMDFMrZFR3MYB2KN3aWimKVI%2FyxAGVUe5N5VmLl3%2BUUH3bDiUTsiqnUjEYnovWrLSsJjC%2Fp5G"}, {"domain": "www.avhd2.com", "expiry": 1557397153.684509, "httpOnly": false, "name": "Hvgv_2132_ulastactivity", "path": "/", "secure": false, "value": "aa16wdTIOj8xvLxPBVW0PXKjwkZMEOBW4%2FvFO4XT5k%2FSIegcDzlh"}, {"domain": "www.avhd2.com", "expiry": 1541585966, "httpOnly": false, "name": "CNZZDATA1260776314", "path": "/", "secure": false, "value": "1992756048-1525859750-%7C1525859750"}, {"domain": "www.avhd2.com", "expiry": 1525861443.914148, "httpOnly": false, "name": "Hvgv_2132_sendmail", "path": "/", "secure": false, "value": "1"}, {"domain": "www.avhd2.com", "expiry": 1525947566.933649, "httpOnly": false, "name": "Hvgv_2132_sid", "path": "/", "secure": false, "value": "Vsz7m9"}, {"domain": "www.avhd2.com", "httpOnly": false, "name": "Hvgv_2132_seccode", "path": "/", "secure": false, "value": "1392.5fd9061393387ad1a4"}, {"domain": "www.avhd2.com", "httpOnly": false, "name": "Hvgv_2132_lip", "path": "/", "secure": false, "value": "116.22.58.182%2C1525861068"}, {"domain": "www.avhd2.com", "expiry": 1525947566.933695, "httpOnly": false, "name": "Hvgv_2132_lastact", "path": "/", "secure": false, "value": "1525861081%09home.php%09spacecp"}, {"domain": "www.avhd2.com", "expiry": 1525861196.933722, "httpOnly": false, "name": "Hvgv_2132_checkpm", "path": "/", "secure": false, "value": "1"}, {"domain": "www.avhd2.com", "expiry": 1525861766, "httpOnly": false, "name": "Hvgv_2132_noticeTitle", "path": "/", "secure": false, "value": "1"}]