[{"domain": "www.i-ab.com", "expiry": 1522684801, "httpOnly": false, "name": "uv_cookie_120452", "path": "/", "secure": false, "value": "1"}, {"domain": ".i-ab.com", "expiry": 1538395820, "httpOnly": false, "name": "UM_distinctid", "path": "/", "secure": false, "value": "1628643eaf1146-01c5cfbd3a72da-3a614f0b-100200-1628643eaf2295"}, {"domain": "www.i-ab.com", "expiry": 1525263017.445074, "httpOnly": true, "name": "gkZp_2132_saltkey", "path": "/", "secure": false, "value": "k4594nNl"}, {"domain": "www.i-ab.com", "expiry": 1525263017.44516, "httpOnly": false, "name": "gkZp_2132_lastvisit", "path": "/", "secure": false, "value": "1522667415"}, {"domain": "www.i-ab.com", "expiry": 1522671319.432706, "httpOnly": false, "name": "gkZp_2132_sendmail", "path": "/", "secure": false, "value": "1"}, {"domain": "www.i-ab.com", "expiry": 1522684802, "httpOnly": false, "name": "uv_cookie_120290", "path": "/", "secure": false, "value": "1"}, {"domain": "www.i-ab.com", "httpOnly": false, "name": "gkZp_2132_creditrule", "path": "/", "secure": false, "value": "%E6%AF%8F%E5%A4%A9%E7%99%BB%E5%BD%95"}, {"domain": "www.i-ab.com", "expiry": 1522757417.445345, "httpOnly": false, "name": "gkZp_2132_pc_size_c", "path": "/", "secure": false, "value": "0"}, {"domain": "www.i-ab.com", "httpOnly": false, "name": "gkZp_2132_seccode", "path": "/", "secure": false, "value": "6398.0ee7b5808bd378d237"}, {"domain": "www.i-ab.com", "expiry": 1522684801, "httpOnly": false, "name": "uv_cookie_120291", "path": "/", "secure": false, "value": "1"}, {"domain": "www.i-ab.com", "expiry": 1838031019, "httpOnly": false, "name": "_uab_collina", "path": "/", "secure": false, "value": "152267101893468971198447"}, {"domain": "www.i-ab.com", "httpOnly": false, "name": "gkZp_2132_creditbase", "path": "/", "secure": false, "value": "0D10D17D0D0D0D0D0D0"}, {"domain": "www.i-ab.com", "expiry": 1522684802, "httpOnly": false, "name": "uv_cookie_120297", "path": "/", "secure": false, "value": "1"}, {"domain": "www.i-ab.com", "expiry": 1538395820, "httpOnly": false, "name": "CNZZDATA1272843567", "path": "/", "secure": false, "value": "89120380-1522669990-%7C1522669990"}, {"domain": "www.i-ab.com", "expiry": 1554207023, "httpOnly": false, "name": "_umdata", "path": "/", "secure": false, "value": "0823A424438F76AB66F3A21E2934608D06AAFA04F23EEAA154FA29A43CE8F88E66588B901190890ACD43AD3E795C914C2562E637215CA2D1FB3542B087AF0A00"}, {"domain": "www.i-ab.com", "expiry": 1522757561.106061, "httpOnly": false, "name": "gkZp_2132_sid", "path": "/", "secure": false, "value": "l4CtCu"}, {"domain": "www.i-ab.com", "expiry": 1522757561.105951, "httpOnly": false, "name": "gkZp_2132_lastact", "path": "/", "secure": false, "value": "1522671158%09member.php%09logging"}, {"domain": "www.i-ab.com", "expiry": 1554207161.106113, "httpOnly": false, "name": "gkZp_2132_ulastactivity", "path": "/", "secure": false, "value": "38f5rHI6%2BMx77VY3DTZsyTQmd6ZbeixMeKoB7LutmnFZJzggFI3c"}, {"domain": "www.i-ab.com", "httpOnly": true, "name": "gkZp_2132_auth", "path": "/", "secure": false, "value": "ab8cQUfoPmLqrmhriD35nd%2FlsvSP7Vs7qOtW13DoWWDlpiCtawv0IY07zZaQ4NWn4EmfZkW0JgnSpfXOolE7hs4s"}, {"domain": "www.i-ab.com", "httpOnly": false, "name": "gkZp_2132_creditnotice", "path": "/", "secure": false, "value": "0D0D2D0D0D0D0D0D0D9654"}, {"domain": "www.i-ab.com", "expiry": 1554207161.106504, "httpOnly": false, "name": "gkZp_2132_lastcheckfeed", "path": "/", "secure": false, "value": "9654%7C1522671158"}, {"domain": "www.i-ab.com", "expiry": 1522671191.106567, "httpOnly": false, "name": "gkZp_2132_checkfollow", "path": "/", "secure": false, "value": "1"}, {"domain": "www.i-ab.com", "httpOnly": false, "name": "gkZp_2132_lip", "path": "/", "secure": false, "value": "116.21.180.140%2C1522483470"}]