[{"domain": "www.taotu99.com", "expiry": 1555422086, "httpOnly": false, "name": "_umdata", "path": "/", "secure": false, "value": "2FB0BDB3C12E491D97BC7EABD4A06446D4DD805855CB1122801C2C83835FEF6613027573C4DC1771CD43AD3E795C914C3BDA6981C1B0BD54F87DAF1FAADA62A8"}, {"domain": "www.taotu99.com", "expiry": 1526478082.629056, "httpOnly": true, "name": "KHxS_2132_saltkey", "path": "/", "secure": false, "value": "Q0FACNNu"}, {"domain": ".taotu99.com", "httpOnly": false, "name": "pgv_info", "path": "/", "secure": false, "value": "ssi=s6240393285"}, {"domain": "www.taotu99.com", "expiry": 1523886383.621946, "httpOnly": false, "name": "KHxS_2132_sendmail", "path": "/", "secure": false, "value": "1"}, {"domain": "www.taotu99.com", "expiry": 1526478082.629157, "httpOnly": false, "name": "KHxS_2132_lastvisit", "path": "/", "secure": false, "value": "1523882477"}, {"domain": "www.taotu99.com", "expiry": 1523972482.629448, "httpOnly": false, "name": "KHxS_2132_pc_size_c", "path": "/", "secure": false, "value": "0"}, {"domain": "www.taotu99.com", "expiry": 1839246083, "httpOnly": false, "name": "_uab_collina", "path": "/", "secure": false, "value": "152388608364124888710942"}, {"domain": ".taotu99.com", "expiry": 2147385600, "httpOnly": false, "name": "pgv_pvi", "path": "/", "secure": false, "value": "7697333492"}, {"domain": "www.taotu99.com", "expiry": 1523972547.708788, "httpOnly": false, "name": "KHxS_2132_sid", "path": "/", "secure": false, "value": "jKukac"}, {"domain": "www.taotu99.com", "httpOnly": true, "name": "KHxS_2132_auth", "path": "/", "secure": false, "value": "57e6dM7O4rCGAc8buBgGgEdJyrzn%2BfqjnJM7jXdG1dF2l%2B8Dmjd%2BJppR2vHFyjDmWHKUhmODtikaVvmle96awsr0"}, {"domain": "www.taotu99.com", "expiry": 1523972547.708587, "httpOnly": false, "name": "KHxS_2132_lastact", "path": "/", "secure": false, "value": "1523886141%09member.php%09logging"}, {"domain": "www.taotu99.com", "expiry": 1555422147.708722, "httpOnly": false, "name": "KHxS_2132_ulastactivity", "path": "/", "secure": false, "value": "7cbfPs8lC9A6ekACq6RtQ7lQPBmjBCRHWIdiLb7N9paWlTZzORXj"}, {"domain": "www.taotu99.com", "expiry": 1555422147.709054, "httpOnly": false, "name": "KHxS_2132_lastcheckfeed", "path": "/", "secure": false, "value": "9009%7C1523886141"}, {"domain": "www.taotu99.com", "expiry": 1523886177.709114, "httpOnly": false, "name": "KHxS_2132_checkfollow", "path": "/", "secure": false, "value": "1"}, {"domain": "www.taotu99.com", "httpOnly": false, "name": "KHxS_2132_lip", "path": "/", "secure": false, "value": "61.140.238.178%2C1523885991"}, {"domain": "www.taotu99.com", "expiry": 1523929347.709215, "httpOnly": false, "name": "KHxS_2132_security_cookiereport", "path": "/", "secure": false, "value": "3b9e%2BKy4eHhuy264XdXf3FGORxcv7YeOSv8czy24uGLep1K6ZK%2BX"}]