[{"domain": "www.366sky.com", "httpOnly": true, "name": "ve9T_2132_seccodeSG8Q7C00", "path": "/", "secure": false, "value": "aef7BrNX%2BKLuK8nXEBqm%2BcNW%2BVxnz2kMJdxqYVawCbFMkz3JAGeSNk0hmmgftonYEeIp1QuNV22xg6nQWbU"}, {"domain": "www.366sky.com", "expiry": 1524714114.0961, "httpOnly": true, "name": "ve9T_2132_saltkey", "path": "/", "secure": false, "value": "qloK1J11"}, {"domain": "www.366sky.com", "expiry": 1522122414.604526, "httpOnly": false, "name": "ve9T_2132_sendmail", "path": "/", "secure": false, "value": "1"}, {"domain": "www.366sky.com", "expiry": 1524714114.096182, "httpOnly": false, "name": "ve9T_2132_lastvisit", "path": "/", "secure": false, "value": "1522118517"}, {"domain": ".366sky.com", "expiry": 1522166394.096418, "httpOnly": false, "name": "safedog-flow-item", "path": "/", "secure": false, "value": "CFB9CAB9F87EBCC59421B0058D18E148"}, {"domain": "www.366sky.com", "expiry": 1522208526.049813, "httpOnly": false, "name": "ve9T_2132_sid", "path": "/", "secure": false, "value": "FDofFU"}, {"domain": "www.366sky.com", "httpOnly": true, "name": "ve9T_2132_auth", "path": "/", "secure": false, "value": "e770zyaWmvAQzlLnsEIhf9eJ4YFsZiZpT02R7nOrvSSk%2B7CwCQJJTyOuDyo%2FUoTEqFoY%2FwcJagMm7OducVCTl8WvOqs"}, {"domain": "www.366sky.com", "expiry": 1522208526.049686, "httpOnly": false, "name": "ve9T_2132_lastact", "path": "/", "secure": false, "value": "1522122129%09member.php%09logging"}, {"domain": "www.366sky.com", "expiry": 1553658126.049868, "httpOnly": false, "name": "ve9T_2132_ulastactivity", "path": "/", "secure": false, "value": "e770zyaWmvAQzlLnsEd2LNaN5t5pNSozHUub6COt6XOk%2BuTkDVRD"}, {"domain": "www.366sky.com", "expiry": 1553658126.050094, "httpOnly": false, "name": "ve9T_2132_lastcheckfeed", "path": "/", "secure": false, "value": "111946%7C1522122129"}, {"domain": "www.366sky.com", "expiry": 1522122156.050156, "httpOnly": false, "name": "ve9T_2132_checkfollow", "path": "/", "secure": false, "value": "1"}, {"domain": "www.366sky.com", "httpOnly": false, "name": "ve9T_2132_lip", "path": "/", "secure": false, "value": "183.54.192.185%2C1522085342"}]