[{"domain": ".shanglin.net", "expiry": 1526403698.559189, "httpOnly": true, "name": "Slin_5402_saltkey", "path": "/", "secure": true, "value": "GHZHyYh9"}, {"domain": ".shanglin.net", "expiry": 1555347740.087243, "httpOnly": false, "name": "Slin_5402_connect_is_bind", "path": "/", "secure": true, "value": "0"}, {"domain": ".shanglin.net", "expiry": 1526403698.55928, "httpOnly": false, "name": "Slin_5402_lastvisit", "path": "/", "secure": true, "value": "1523808094"}, {"domain": ".shanglin.net", "expiry": 1523811999.221859, "httpOnly": false, "name": "Slin_5402_sendmail", "path": "/", "secure": true, "value": "1"}, {"domain": ".shanglin.net", "expiry": 1523898140.087139, "httpOnly": false, "name": "Slin_5402_lastact", "path": "/", "secure": true, "value": "1523811736%09connect.php%09check"}, {"domain": ".shanglin.net", "httpOnly": false, "name": "Slin_5402_seccode", "path": "/", "secure": true, "value": "7.4fcd49aec6e4b41389"}, {"domain": ".shanglin.net", "expiry": 1523898134.335241, "httpOnly": false, "name": "Slin_5402_myrepeat_rr", "path": "/", "secure": true, "value": "R0"}, {"domain": ".shanglin.net", "httpOnly": true, "name": "Slin_5402_auth", "path": "/", "secure": true, "value": "388ec1g9RDTlP7xX%2B0h6mJ61HyUqsgZMVSehmPTwnH7LmEGJZPUUGbuUeYSxyv%2FQaF%2Fo5XV2f6J5kUsZegVdWtzi1dM"}, {"domain": ".shanglin.net", "expiry": 1555347734.334642, "httpOnly": false, "name": "Slin_5402_ulastactivity", "path": "/", "secure": true, "value": "1523811730%7C0"}, {"domain": ".shanglin.net", "expiry": 1523811768.117774, "httpOnly": false, "name": "Slin_5402_checkpm", "path": "/", "secure": true, "value": "1"}, {"domain": ".shanglin.net", "expiry": 1523812338, "httpOnly": false, "name": "Slin_5402_noticeTitle", "path": "/", "secure": false, "value": "1"}]