[{"domain": "www.vrzhixin.com", "expiry": 1528354218.834793, "httpOnly": true, "name": "nTfg_2132_saltkey", "path": "/", "secure": false, "value": "L0EA4Um1"}, {"domain": "www.vrzhixin.com", "expiry": 1528354218.834824, "httpOnly": false, "name": "nTfg_2132_lastvisit", "path": "/", "secure": false, "value": "1525758621"}, {"domain": "www.vrzhixin.com", "expiry": 1525848635.072105, "httpOnly": false, "name": "nTfg_2132_sid", "path": "/", "secure": false, "value": "f8HqxQ"}, {"domain": "www.vrzhixin.com", "expiry": 1541487035, "httpOnly": false, "name": "CNZZDATA1271463956", "path": "/", "secure": false, "value": "484738013-1525762222-%7C1525762222"}, {"domain": ".vrzhixin.com", "expiry": 1541487020, "httpOnly": false, "name": "UM_distinctid", "path": "/", "secure": false, "value": "1633e83e14e40d-04b79b62a6aa83-3961430f-1fa400-1633e83e14f1e1"}, {"domain": "www.vrzhixin.com", "expiry": 1525762520.372505, "httpOnly": false, "name": "nTfg_2132_sendmail", "path": "/", "secure": false, "value": "1"}, {"domain": ".vrzhixin.com", "expiry": 1557298235, "httpOnly": false, "name": "Hm_lvt_efbf32c6d831f43a5c506be17ec397a3", "path": "/", "secure": false, "value": "1525762221"}, {"domain": "www.vrzhixin.com", "expiry": 1651992621, "httpOnly": false, "name": "bdshare_firstime", "path": "/", "secure": false, "value": "1525762221185"}, {"domain": "www.vrzhixin.com", "httpOnly": false, "name": "nTfg_2132_seccode", "path": "/", "secure": false, "value": "1.c06859269975c7e9e7"}, {"domain": "www.vrzhixin.com", "expiry": 1557298231.641548, "httpOnly": false, "name": "nTfg_2132_ulastactivity", "path": "/", "secure": false, "value": "efe4xG5FxpSYFgv4RFCNkoUDse2XTbRUY5p%2FVe2CxXgn5I1g82wT"}, {"domain": "www.vrzhixin.com", "httpOnly": true, "name": "nTfg_2132_auth", "path": "/", "secure": false, "value": "7c8bV2q67Zog30SzAYkKs6dGRG4PpAk93qHo3oFVgvqJSEghUHluTzc1SnchOWVxYdsZYhYcbzsen4ekTveGYVOW"}, {"domain": "www.vrzhixin.com", "expiry": 1557298235.072065, "httpOnly": false, "name": "nTfg_2132_nofavfid", "path": "/", "secure": false, "value": "1"}, {"domain": "www.vrzhixin.com", "expiry": 1525762535.072084, "httpOnly": false, "name": "nTfg_2132_onlineusernum", "path": "/", "secure": false, "value": "14"}, {"domain": ".vrzhixin.com", "httpOnly": false, "name": "Hm_lpvt_efbf32c6d831f43a5c506be17ec397a3", "path": "/", "secure": false, "value": "1525762236"}, {"domain": "www.vrzhixin.com", "expiry": 1525848635.627713, "httpOnly": false, "name": "nTfg_2132_lastact", "path": "/", "secure": false, "value": "1525762238%09home.php%09spacecp"}, {"domain": "www.vrzhixin.com", "expiry": 1525762265.627756, "httpOnly": false, "name": "nTfg_2132_checkpm", "path": "/", "secure": false, "value": "1"}, {"domain": "www.vrzhixin.com", "expiry": 1525762835, "httpOnly": false, "name": "nTfg_2132_noticeTitle", "path": "/", "secure": false, "value": "1"}]