[{"domain": ".anbeiwang.com", "httpOnly": false, "name": "CnNx_c985_creditnotice", "path": "/", "secure": false, "value": "0D0D2D0D0D0D0D0D0D226308"}, {"domain": ".anbeiwang.com", "expiry": 1523804712.314459, "httpOnly": false, "name": "CnNx_c985_sendmail", "path": "/", "secure": false, "value": "1"}, {"domain": ".anbeiwang.com", "expiry": 1526396404.34368, "httpOnly": false, "name": "CnNx_c985_lastvisit", "path": "/", "secure": false, "value": "1523800561"}, {"domain": ".anbeiwang.com", "expiry": 1526396404.343571, "httpOnly": true, "name": "CnNx_c985_saltkey", "path": "/", "secure": false, "value": "JylrxkR9"}, {"domain": ".anbeiwang.com", "expiry": 1523804760.363427, "httpOnly": false, "name": "CnNx_c985_onlineusernum", "path": "/", "secure": false, "value": "1236"}, {"domain": ".anbeiwang.com", "httpOnly": false, "name": "CnNx_c985_secqaa", "path": "/", "secure": false, "value": "403.4a79f10896e823f752"}, {"domain": ".anbeiwang.com", "httpOnly": true, "name": "CnNx_c985_auth", "path": "/", "secure": false, "value": "0ea3wc%2F1S95vVI%2FbWFR4MIEX%2F7oQKii13R6g2KzIwgt27rC%2FH7YFH24nQvrrhw7nscurk5DoVshvsCzNbxTl90orYis"}, {"domain": ".anbeiwang.com", "expiry": 1523890885.037436, "httpOnly": false, "name": "CnNx_c985_lastact", "path": "/", "secure": false, "value": "1523804241%09misc.php%09patch"}, {"domain": ".anbeiwang.com", "httpOnly": false, "name": "CnNx_c985_seccode", "path": "/", "secure": false, "value": "404.ddb62565b1220363bb"}, {"domain": ".anbeiwang.com", "expiry": 1555340450.290379, "httpOnly": false, "name": "CnNx_c985_ulastactivity", "path": "/", "secure": false, "value": "d1127Ap0uHxmCZRCIBimDpIJZegoE8eSn7gEc2iuEv0DTK9zNwXI"}, {"domain": ".anbeiwang.com", "httpOnly": false, "name": "CnNx_c985_creditbase", "path": "/", "secure": false, "value": "0D50D50D0D0D0D0D0D0"}, {"domain": ".anbeiwang.com", "httpOnly": false, "name": "CnNx_c985_creditrule", "path": "/", "secure": false, "value": "%E6%AF%8F%E5%A4%A9%E7%99%BB%E5%BD%95"}, {"domain": ".anbeiwang.com", "expiry": 1555340485.037503, "httpOnly": false, "name": "CnNx_c985_connect_is_bind", "path": "/", "secure": false, "value": "0"}, {"domain": ".anbeiwang.com", "expiry": 1523847660.363264, "httpOnly": false, "name": "CnNx_c985_security_cookiereport", "path": "/", "secure": false, "value": "6814ZiKL7bMxi6M9KfCTfTyFdD7wHUhb%2FREejVQ4VF8WCwdT5MKN"}, {"domain": ".anbeiwang.com", "expiry": 1555340460.363351, "httpOnly": false, "name": "CnNx_c985_nofavfid", "path": "/", "secure": false, "value": "1"}, {"domain": ".anbeiwang.com", "expiry": 1523804493.621358, "httpOnly": false, "name": "CnNx_c985_checkpm", "path": "/", "secure": false, "value": "1"}, {"domain": ".anbeiwang.com", "expiry": 1523805084, "httpOnly": false, "name": "CnNx_c985_noticeTitle", "path": "/", "secure": false, "value": "1"}, {"domain": "www.anbeiwang.com", "expiry": 1523890884, "httpOnly": false, "name": "ad_play_index", "path": "/", "secure": false, "value": "47"}, {"domain": ".anbeiwang.com", "expiry": 1523890885.037281, "httpOnly": false, "name": "CnNx_c985_sid", "path": "/", "secure": false, "value": "JzfiG4"}, {"domain": ".anbeiwang.com", "httpOnly": false, "name": "CnNx_c985_lip", "path": "/", "secure": false, "value": "113.65.160.252%2C1523804240"}]