[{"domain": ".6699dh.xyz", "expiry": 1555050713.657911, "httpOnly": true, "name": "__cfduid", "path": "/", "secure": false, "value": "da84f95a4af5f1e96ab97acf8e676bff31523514709"}, {"domain": "www.6699dh.xyz", "expiry": 1526106713.65805, "httpOnly": false, "name": "gqYl_2132_lastvisit", "path": "/", "secure": false, "value": "1523511109"}, {"domain": "www.6699dh.xyz", "expiry": 1526106713.657996, "httpOnly": true, "name": "gqYl_2132_saltkey", "path": "/", "secure": false, "value": "IewUFAd4"}, {"domain": ".6699dh.xyz", "expiry": 1523601151, "httpOnly": false, "name": "_gid", "path": "/", "secure": false, "value": "GA1.2.1858584603.1523514716"}, {"domain": ".6699dh.xyz", "expiry": 1586586751, "httpOnly": false, "name": "_ga", "path": "/", "secure": false, "value": "GA1.2.1638071084.1523514716"}, {"domain": "www.6699dh.xyz", "expiry": 1523515015.28558, "httpOnly": false, "name": "gqYl_2132_sendmail", "path": "/", "secure": false, "value": "1"}, {"domain": "www.6699dh.xyz", "expiry": 1523601152.081243, "httpOnly": false, "name": "gqYl_2132_lastact", "path": "/", "secure": false, "value": "1523514747%09home.php%09spacecp"}, {"domain": "www.6699dh.xyz", "httpOnly": false, "name": "gqYl_2132_seccode", "path": "/", "secure": false, "value": "1.437f37bccafb6e9958"}, {"domain": ".6699dh.xyz", "expiry": 1523514775, "httpOnly": false, "name": "_gat_gtag_UA_116767609_7", "path": "/", "secure": false, "value": "1"}, {"domain": "www.6699dh.xyz", "expiry": 1555050746.472113, "httpOnly": false, "name": "gqYl_2132_ulastactivity", "path": "/", "secure": false, "value": "1e0bs5HZ%2FlRgN9jASiRdMKWhNSckXG84E45DfutC6ukuX7Wv5oM1"}, {"domain": "www.6699dh.xyz", "httpOnly": true, "name": "gqYl_2132_auth", "path": "/", "secure": false, "value": "139djEGAkqFLyfem29rMP%2Bl2dG8eiKlKhWSfFfeQOxOs6ObCqUpRSwk5xpn2i1jabjtf8bDVTNNgVvlUW1cm"}, {"domain": "www.6699dh.xyz", "expiry": 1555050751.032493, "httpOnly": false, "name": "gqYl_2132_nofavfid", "path": "/", "secure": false, "value": "1"}, {"domain": "www.6699dh.xyz", "expiry": 1523515051.032552, "httpOnly": false, "name": "gqYl_2132_onlineusernum", "path": "/", "secure": false, "value": "99"}, {"domain": "www.6699dh.xyz", "expiry": 1523601152.08116, "httpOnly": false, "name": "gqYl_2132_sid", "path": "/", "secure": false, "value": "IvNBVV"}, {"domain": "www.6699dh.xyz", "httpOnly": false, "name": "gqYl_2132_lip", "path": "/", "secure": false, "value": "116.23.154.193%2C1523514747"}, {"domain": "www.6699dh.xyz", "expiry": 1523514782.081305, "httpOnly": false, "name": "gqYl_2132_checkpm", "path": "/", "secure": false, "value": "1"}, {"domain": "www.6699dh.xyz", "expiry": 1523515352, "httpOnly": false, "name": "gqYl_2132_noticeTitle", "path": "/", "secure": false, "value": "1"}]