[{"domain": "zmsjiepai.com", "expiry": 1538586920, "httpOnly": false, "name": "CNZZDATA1264503728", "path": "/", "secure": false, "value": "1110360264-1522861843-%7C1522861843"}, {"domain": "zmsjiepai.com", "expiry": 1522862420.387665, "httpOnly": false, "name": "IKkK_2132_sendmail", "path": "/", "secure": false, "value": "1"}, {"domain": "zmsjiepai.com", "expiry": 1525454120.05972, "httpOnly": false, "name": "IKkK_2132_lastvisit", "path": "/", "secure": false, "value": "1522858505"}, {"domain": "zmsjiepai.com", "expiry": 1525454120.05966, "httpOnly": true, "name": "IKkK_2132_saltkey", "path": "/", "secure": false, "value": "CXwHhplP"}, {"domain": ".zmsjiepai.com", "expiry": 1538586920, "httpOnly": false, "name": "UM_distinctid", "path": "/", "secure": false, "value": "16291a7df3419e-0e8336637df813-3a614f0b-100200-16291a7df358f"}, {"domain": "zmsjiepai.com", "expiry": 1538586920, "httpOnly": false, "name": "CNZZDATA1253091190", "path": "/", "secure": false, "value": "1919851378-1522859020-%7C1522859020"}, {"domain": "zmsjiepai.com", "httpOnly": true, "name": "IKkK_2132_auth", "path": "/", "secure": false, "value": "b0deiL1I%2BC7%2FzLnMulP08H7wRT5pZ6zrqZGvbPhBqGosIh7yQF9YahZr77azCHQ9eZUBuDelXgyScLWfYBl75ijNbOY"}, {"domain": "zmsjiepai.com", "expiry": 1522948566.689525, "httpOnly": false, "name": "IKkK_2132_lastact", "path": "/", "secure": false, "value": "1522862152%09member.php%09logging"}, {"domain": "zmsjiepai.com", "expiry": 1522948566.689732, "httpOnly": false, "name": "IKkK_2132_sid", "path": "/", "secure": false, "value": "JvvFWe"}, {"domain": "zmsjiepai.com", "httpOnly": false, "name": "IKkK_2132_seccode", "path": "/", "secure": false, "value": "1249.7679f4d3790d51ab06"}, {"domain": "zmsjiepai.com", "expiry": 1554398166.689656, "httpOnly": false, "name": "IKkK_2132_ulastactivity", "path": "/", "secure": false, "value": "e882fRPWm6kbA2AeSCO%2BGrIdLW65t8jd41WHVEJ5LkSLWRhSrq3m"}, {"domain": "zmsjiepai.com", "expiry": 1554398166.690053, "httpOnly": false, "name": "IKkK_2132_lastcheckfeed", "path": "/", "secure": false, "value": "126359%7C1522862152"}, {"domain": "zmsjiepai.com", "expiry": 1522862196.690116, "httpOnly": false, "name": "IKkK_2132_checkfollow", "path": "/", "secure": false, "value": "1"}, {"domain": "zmsjiepai.com", "httpOnly": false, "name": "IKkK_2132_lip", "path": "/", "secure": false, "value": "116.22.58.207%2C1522862083"}, {"domain": "zmsjiepai.com", "expiry": 1522905366.690234, "httpOnly": false, "name": "IKkK_2132_security_cookiereport", "path": "/", "secure": false, "value": "c6festmsRZs01L6sJFZLb1PLOxWSl%2FAhP4UHoHEvwvuZoWSToemM"}]