[{"domain": "www.makemodelsua.com", "expiry": 1553538384.547792, "httpOnly": false, "name": "nC26_2132_nofavfid", "path": "/", "secure": false, "value": "1"}, {"domain": "www.makemodelsua.com", "expiry": 1524594365.751999, "httpOnly": true, "name": "nC26_2132_saltkey", "path": "/", "secure": false, "value": "MChtyNhH"}, {"domain": "www.makemodelsua.com", "expiry": 1524594365.75212, "httpOnly": false, "name": "nC26_2132_lastvisit", "path": "/", "secure": false, "value": "1521998765"}, {"domain": "www.makemodelsua.com", "expiry": 1522045584.547685, "httpOnly": false, "name": "nC26_2132_security_cookiereport", "path": "/", "secure": false, "value": "546e4m78tD5yE11q0kmZ27mfSazwXIGNHVd3yqybsffr%2By7aOhrH"}, {"domain": "www.makemodelsua.com", "expiry": 1522002666.511409, "httpOnly": false, "name": "nC26_2132_sendmail", "path": "/", "secure": false, "value": "1"}, {"domain": "www.makemodelsua.com", "expiry": 1522088784.547983, "httpOnly": false, "name": "nC26_2132_sid", "path": "/", "secure": false, "value": "khbFyW"}, {"domain": "www.makemodelsua.com", "httpOnly": true, "name": "nC26_2132_auth", "path": "/", "secure": false, "value": "95ffMH53saF8txqG8ERcVDQiMP397F%2FK%2B%2FgkP0kDlzSToA%2BLuuJCIJ29UfXEcJD2LJFZ1kArsZmgbgNIPfdxPxjNAQ"}, {"domain": "www.makemodelsua.com", "expiry": 1553538379.011353, "httpOnly": false, "name": "nC26_2132_ulastactivity", "path": "/", "secure": false, "value": "217eBqldLxZTpE4NnmiWYpxvD%2FrD85UYbniRJgE6g9sOflRF%2B41W"}, {"domain": "www.makemodelsua.com", "expiry": 1522002684.547892, "httpOnly": false, "name": "nC26_2132_onlineusernum", "path": "/", "secure": false, "value": "153"}, {"domain": "www.makemodelsua.com", "expiry": 1522088785.951455, "httpOnly": false, "name": "nC26_2132_lastact", "path": "/", "secure": false, "value": "1522002385%09home.php%09spacecp"}, {"domain": "www.makemodelsua.com", "expiry": 1522002415.951575, "httpOnly": false, "name": "nC26_2132_checkpm", "path": "/", "secure": false, "value": "1"}, {"domain": "www.makemodelsua.com", "expiry": 1522002986, "httpOnly": false, "name": "nC26_2132_noticeTitle", "path": "/", "secure": false, "value": "1"}]