[{"domain": "www.shapablesoft.com", "httpOnly": false, "name": "nb-referrer-hostname", "path": "/", "secure": false, "value": "www.shapablesoft.com"}, {"domain": "www.shapablesoft.com", "expiry": 1521776215.69812, "httpOnly": false, "name": "eiQH_2132_checkpm", "path": "/", "secure": false, "value": "1"}, {"domain": "www.shapablesoft.com", "expiry": 1553312185.698055, "httpOnly": false, "name": "eiQH_2132_connect_is_bind", "path": "/", "secure": false, "value": "0"}, {"domain": "www.shapablesoft.com", "expiry": 1524368159.488085, "httpOnly": true, "name": "eiQH_2132_saltkey", "path": "/", "secure": false, "value": "d3G1VAmx"}, {"domain": "www.shapablesoft.com", "expiry": 1524368159.488127, "httpOnly": false, "name": "eiQH_2132_lastvisit", "path": "/", "secure": false, "value": "1521772558"}, {"domain": ".shapablesoft.com", "expiry": 1521820799.48827, "httpOnly": false, "name": "safedog-flow-item", "path": "/", "secure": false, "value": "EBE93D2A0474437431738EB2AB4D4AB1"}, {"domain": ".shapablesoft.com", "expiry": 1553312191, "httpOnly": false, "name": "Hm_lvt_7e1f47264ea09fbc4c918a58433f9971", "path": "/", "secure": false, "value": "1521776161"}, {"domain": "www.shapablesoft.com", "expiry": 1521862585.698026, "httpOnly": false, "name": "eiQH_2132_lastact", "path": "/", "secure": false, "value": "1521776183%09home.php%09spacecp"}, {"domain": "www.shapablesoft.com", "httpOnly": false, "name": "eiQH_2132_seccode", "path": "/", "secure": false, "value": "32.21ae47930d78cedb92"}, {"domain": "www.shapablesoft.com", "expiry": 1521776461.358477, "httpOnly": false, "name": "eiQH_2132_sendmail", "path": "/", "secure": false, "value": "1"}, {"domain": "www.shapablesoft.com", "expiry": 1537500984, "httpOnly": false, "name": "CNZZDATA1257345922", "path": "/", "secure": false, "value": "1783554933-1521775859-%7C1521775859"}, {"domain": ".shapablesoft.com", "expiry": 1537500960, "httpOnly": false, "name": "UM_distinctid", "path": "/", "secure": false, "value": "16250ed6fd6716-0f1b50cbd818ce-5f4f2816-1fa400-16250ed6fd7577"}, {"domain": "www.shapablesoft.com", "httpOnly": false, "name": "nb-start-page-url", "path": "/", "secure": false, "value": "http%3A%2F%2Fwww.shapablesoft.com%2Fmember.php%3Fmod%3Dregister"}, {"domain": "www.shapablesoft.com", "expiry": 1553312182.278324, "httpOnly": false, "name": "eiQH_2132_ulastactivity", "path": "/", "secure": false, "value": "df05NsFih%2Bvy7DXnH5dfyypWYkF%2BCcJJdRj1UVGJMByukou7zefw"}, {"domain": ".shapablesoft.com", "httpOnly": false, "name": "Hm_lpvt_7e1f47264ea09fbc4c918a58433f9971", "path": "/", "secure": false, "value": "1521776191"}, {"domain": "www.shapablesoft.com", "httpOnly": true, "name": "eiQH_2132_auth", "path": "/", "secure": false, "value": "41eaWGaaRXgrVHw4s4qPBXGo7uylY8VZmE78hL9lUi1xowb%2F19aN9lZmcRZSWZDr9fEhdltc%2BpQjb8V4woGv7aL%2FbA"}, {"domain": "www.shapablesoft.com", "httpOnly": false, "name": "eiQH_2132_creditnotice", "path": "/", "secure": false, "value": "0D0D2D0D0D0D0D0D0D26782"}, {"domain": "www.shapablesoft.com", "httpOnly": false, "name": "eiQH_2132_creditbase", "path": "/", "secure": false, "value": "0D0D0D0D0D0D0D0D0"}, {"domain": "www.shapablesoft.com", "httpOnly": false, "name": "eiQH_2132_creditrule", "path": "/", "secure": false, "value": "%E6%AF%8F%E5%A4%A9%E7%99%BB%E5%BD%95"}, {"domain": "www.shapablesoft.com", "expiry": 1521862585.697966, "httpOnly": false, "name": "eiQH_2132_sid", "path": "/", "secure": false, "value": "sj6tLk"}, {"domain": "www.shapablesoft.com", "httpOnly": false, "name": "eiQH_2132_lip", "path": "/", "secure": false, "value": "61.140.233.220%2C1521776180"}, {"domain": "www.shapablesoft.com", "expiry": 1521776784, "httpOnly": false, "name": "eiQH_2132_noticeTitle", "path": "/", "secure": false, "value": "1"}]