[{"domain": "www.avhd2.com", "expiry": 1524295400.950589, "httpOnly": true, "name": "Hvgv_2132_saltkey", "path": "/", "secure": false, "value": "KvuauiMO"}, {"domain": "www.avhd2.com", "expiry": 1524295400.950626, "httpOnly": false, "name": "Hvgv_2132_lastvisit", "path": "/", "secure": false, "value": "1521699801"}, {"domain": "www.avhd2.com", "expiry": 1521703703.354017, "httpOnly": false, "name": "Hvgv_2132_sendmail", "path": "/", "secure": false, "value": "1"}, {"domain": ".avhd2.com", "expiry": 1537428203, "httpOnly": false, "name": "UM_distinctid", "path": "/", "secure": false, "value": "1624c97402853a-0a6afa69112792-5f4f2816-1fa400-1624c974029269"}, {"domain": "www.avhd2.com", "httpOnly": true, "name": "Hvgv_2132_auth", "path": "/", "secure": false, "value": "1ee6d6R3WFvXq4VZq85tggajX35T6z8nVrw3R2vSewLgERUW32vpVP7woMf3e5HIMot%2FtmqH2ZsT9n8KxKGybXM0crk"}, {"domain": "www.avhd2.com", "expiry": 1553239434.789674, "httpOnly": false, "name": "Hvgv_2132_ulastactivity", "path": "/", "secure": false, "value": "7c10w3UqTAruRSc9Y2VlYrD5TCd7ZB3kIcTCpkKfGbJQN6CHhjgJ"}, {"domain": "www.avhd2.com", "expiry": 1537428240, "httpOnly": false, "name": "CNZZDATA1260776314", "path": "/", "secure": false, "value": "737530893-1521698430-%7C1521698430"}, {"domain": "www.avhd2.com", "expiry": 1521789839.166309, "httpOnly": false, "name": "Hvgv_2132_sid", "path": "/", "secure": false, "value": "eg7oNN"}, {"domain": "www.avhd2.com", "httpOnly": false, "name": "Hvgv_2132_seccode", "path": "/", "secure": false, "value": "1275.adb50fdb1f522729f6"}, {"domain": "www.avhd2.com", "expiry": 1521789839.547822, "httpOnly": false, "name": "Hvgv_2132_lastact", "path": "/", "secure": false, "value": "1521703439%09home.php%09spacecp"}, {"domain": "www.avhd2.com", "expiry": 1521703469.547858, "httpOnly": false, "name": "Hvgv_2132_checkpm", "path": "/", "secure": false, "value": "1"}, {"domain": "www.avhd2.com", "expiry": 1521704040, "httpOnly": false, "name": "Hvgv_2132_noticeTitle", "path": "/", "secure": false, "value": "1"}]