[{"domain": "www.qun123.net", "expiry": 1525337424.253932, "httpOnly": false, "name": "pr2R_2132_lastvisit", "path": "/", "secure": false, "value": "1522741822"}, {"domain": "www.qun123.net", "expiry": 1522745726.254736, "httpOnly": false, "name": "pr2R_2132_sendmail", "path": "/", "secure": false, "value": "1"}, {"domain": "www.qun123.net", "httpOnly": false, "name": "hasshown", "path": "/", "secure": false, "value": "1"}, {"domain": "www.qun123.net", "expiry": 1525337424.253836, "httpOnly": true, "name": "pr2R_2132_saltkey", "path": "/", "secure": false, "value": "SEY0QcFC"}, {"domain": "www.qun123.net", "httpOnly": false, "name": "pr2R_2132_creditrule", "path": "/", "secure": false, "value": "%E6%AF%8F%E5%A4%A9%E7%99%BB%E5%BD%95"}, {"domain": "www.qun123.net", "expiry": 1522831824.254116, "httpOnly": false, "name": "pr2R_2132_pc_size_c", "path": "/", "secure": false, "value": "0"}, {"domain": "www.qun123.net", "expiry": 1838105425, "httpOnly": false, "name": "_uab_collina", "path": "/", "secure": false, "value": "152274542496278733148198"}, {"domain": "www.qun123.net", "expiry": 1538470246, "httpOnly": false, "name": "CNZZDATA1260795442", "path": "/", "secure": false, "value": "272317419-1522743765-%7C1522743765"}, {"domain": ".qun123.net", "expiry": 1538470225, "httpOnly": false, "name": "UM_distinctid", "path": "/", "secure": false, "value": "1628ab33e9ab5-0abf0b1b0af8df-3a614f0b-100200-1628ab33e9b3d"}, {"domain": ".qun123.net", "expiry": 1554281446, "httpOnly": false, "name": "Hm_lvt_0e53ae2e6f895cf1972606870ebc3604", "path": "/", "secure": false, "value": "1522745426"}, {"domain": ".qun123.net", "expiry": 1554281447, "httpOnly": false, "name": "Hm_lvt_13991aa960e89eccd0a3c6fc8fd5a62d", "path": "/", "secure": false, "value": "1522745426"}, {"domain": "www.qun123.net", "expiry": 1554281427, "httpOnly": false, "name": "_umdata", "path": "/", "secure": false, "value": "6AF5B463492A874DAD51E463E812966C72637AA72E10953D6E722313BD5231EB7B7BAD482156914ACD43AD3E795C914C4566E5438696F19FFD363D61E43AF014"}, {"domain": "www.qun123.net", "expiry": 1522746046, "httpOnly": false, "name": "pr2R_2132_noticeTitle", "path": "/", "secure": false, "value": "1"}, {"domain": "www.qun123.net", "expiry": 1554281440.123384, "httpOnly": false, "name": "pr2R_2132_ulastactivity", "path": "/", "secure": false, "value": "a1fdKwCXbmzrlkKoYHa1V8kFZeCsIHeBI5RtsDEjzJYD3TDW9Sbm"}, {"domain": "www.qun123.net", "expiry": 1522831846.594388, "httpOnly": false, "name": "pr2R_2132_sid", "path": "/", "secure": false, "value": "wljxJg"}, {"domain": "www.qun123.net", "httpOnly": true, "name": "pr2R_2132_auth", "path": "/", "secure": false, "value": "a1fdKwCXbmzrlkKoYHa2BcgOYOCqdnKGcJE%2B5joqmJMI0mCConTqgM7RjBvSiPDYjPT8wZ7V84mpLSTmk1PP5LAF"}, {"domain": "www.qun123.net", "httpOnly": false, "name": "pr2R_2132_creditnotice", "path": "/", "secure": false, "value": "0D0D2D0D0D0D0D0D0D3894"}, {"domain": "www.qun123.net", "httpOnly": false, "name": "pr2R_2132_creditbase", "path": "/", "secure": false, "value": "0D0D0D0D0D0D0D0D0"}, {"domain": "www.qun123.net", "expiry": 1554281446.59459, "httpOnly": false, "name": "pr2R_2132_connect_is_bind", "path": "/", "secure": false, "value": "0"}, {"domain": "www.qun123.net", "httpOnly": false, "name": "pr2R_2132_lip", "path": "/", "secure": false, "value": "61.140.234.235%2C1522745443"}, {"domain": "www.qun123.net", "expiry": 1522831846.594523, "httpOnly": false, "name": "pr2R_2132_lastact", "path": "/", "secure": false, "value": "1522745444%09home.php%09spacecp"}, {"domain": "www.qun123.net", "expiry": 1522745476.594656, "httpOnly": false, "name": "pr2R_2132_checkpm", "path": "/", "secure": false, "value": "1"}, {"domain": ".qun123.net", "httpOnly": false, "name": "Hm_lpvt_0e53ae2e6f895cf1972606870ebc3604", "path": "/", "secure": false, "value": "1522745446"}, {"domain": ".qun123.net", "httpOnly": false, "name": "Hm_lpvt_13991aa960e89eccd0a3c6fc8fd5a62d", "path": "/", "secure": false, "value": "1522745448"}]