[{"domain": "www.cnscg.com", "expiry": 1527150277.125227, "httpOnly": true, "name": "KTVg_2132_saltkey", "path": "/", "secure": false, "value": "WpJj7K26"}, {"domain": "www.cnscg.com", "expiry": 1527150277.125314, "httpOnly": false, "name": "KTVg_2132_lastvisit", "path": "/", "secure": false, "value": "1524554665"}, {"domain": ".cnscg.com", "expiry": 1540283078, "httpOnly": false, "name": "UM_distinctid", "path": "/", "secure": false, "value": "162f6c13023c5-0b00f257254465-3a614f0b-100200-162f6c130241bd"}, {"domain": "www.cnscg.com", "expiry": 1556094280, "httpOnly": false, "name": "_umdata", "path": "/", "secure": false, "value": "2FB0BDB3C12E491DD91FFA3F2B3348279C9FDC98696849784637FAD33EBC8A65DA7ECC37E8CBAFC5CD43AD3E795C914C652ACE23B6283ACFD93C33A5D2F8F474"}, {"domain": "www.cnscg.com", "expiry": 1524644677.125432, "httpOnly": false, "name": "KTVg_2132_pc_size_c", "path": "/", "secure": false, "value": "0"}, {"domain": "www.cnscg.com", "expiry": 1540283078, "httpOnly": false, "name": "CNZZDATA1261257029", "path": "/", "secure": false, "value": "921347034-1524554212-%7C1524554212"}, {"domain": "www.cnscg.com", "expiry": 1839918278, "httpOnly": false, "name": "_uab_collina", "path": "/", "secure": false, "value": "152455827845028749404648"}, {"domain": "www.cnscg.com", "expiry": 1524644709.790535, "httpOnly": false, "name": "KTVg_2132_lastact", "path": "/", "secure": false, "value": "1524558297%09member.php%09logging"}, {"domain": "www.cnscg.com", "expiry": 1556094309.790629, "httpOnly": false, "name": "KTVg_2132_ulastactivity", "path": "/", "secure": false, "value": "1524558297%7C0"}, {"domain": "www.cnscg.com", "httpOnly": true, "name": "KTVg_2132_auth", "path": "/", "secure": false, "value": "e8d5seNOGq9r%2FQ15vhtYcLFWrpsTSMPomxY9zk7Vocdv%2FvXoaWMPf5%2Bs3pB%2BJT%2Foa%2BOG5%2B9vf8PM75gyAqM1lqolC7Sm"}, {"domain": "www.cnscg.com", "expiry": 1556094309.790885, "httpOnly": false, "name": "KTVg_2132_lastcheckfeed", "path": "/", "secure": false, "value": "2922406%7C1524558297"}, {"domain": "www.cnscg.com", "expiry": 1524558339.790935, "httpOnly": false, "name": "KTVg_2132_checkfollow", "path": "/", "secure": false, "value": "1"}, {"domain": "www.cnscg.com", "httpOnly": false, "name": "KTVg_2132_lip", "path": "/", "secure": false, "value": "113.67.72.183%2C1524558297"}]