[{"domain": "www.seacms.net", "httpOnly": false, "name": "DbTj_2132_creditnotice", "path": "/", "secure": false, "value": "0D2D2D0D0D0D0D0D0D21753"}, {"domain": "www.seacms.net", "expiry": 1524671073.854654, "httpOnly": true, "name": "DbTj_2132_saltkey", "path": "/", "secure": false, "value": "OlLIKqlI"}, {"domain": "www.seacms.net", "httpOnly": false, "name": "DbTj_2132_tshuz_lang", "path": "/", "secure": false, "value": "fb5ao%2Fuu0RGPjoarEgKwYFWuNGeBXVRsGI%2B3zZqY0lVwaAI"}, {"domain": "www.seacms.net", "expiry": 1553615220.23394, "httpOnly": false, "name": "DbTj_2132_connect_is_bind", "path": "/", "secure": false, "value": "0"}, {"domain": "www.seacms.net", "expiry": 1522079373.077652, "httpOnly": false, "name": "DbTj_2132_sendmail", "path": "/", "secure": false, "value": "1"}, {"domain": "www.seacms.net", "expiry": 1524671073.854842, "httpOnly": false, "name": "DbTj_2132_lastvisit", "path": "/", "secure": false, "value": "1522075473"}, {"domain": "www.seacms.net", "httpOnly": true, "name": "PHPSESSID", "path": "/", "secure": false, "value": "m0a1i9rlufqd9f8roqir2m6ma94nns0e"}, {"domain": "www.seacms.net", "httpOnly": false, "name": "DbTj_2132_seccode", "path": "/", "secure": false, "value": "1530.114ef60eb3269c0a2c"}, {"domain": "www.seacms.net", "expiry": 1553615216.608355, "httpOnly": false, "name": "DbTj_2132_ulastactivity", "path": "/", "secure": false, "value": "1522079216%7C0"}, {"domain": "www.seacms.net", "expiry": 1522079520.006887, "httpOnly": false, "name": "DbTj_2132_onlineusernum", "path": "/", "secure": false, "value": "59"}, {"domain": "www.seacms.net", "httpOnly": true, "name": "DbTj_2132_auth", "path": "/", "secure": false, "value": "b756TK6WRPunxO%2FJJHRxAjz5Mq8rYA9OuVvl4c8UupiDfWI0RjtV44lX0H2R8imbw1P7TyXD94WCZLCU5IbKjjmYSQ"}, {"domain": "www.seacms.net", "httpOnly": false, "name": "DbTj_2132_creditbase", "path": "/", "secure": false, "value": "0D0D0D0D0D0D0D0D0"}, {"domain": "www.seacms.net", "expiry": 1553615220.006753, "httpOnly": false, "name": "DbTj_2132_nofavfid", "path": "/", "secure": false, "value": "1"}, {"domain": "www.seacms.net", "httpOnly": false, "name": "DbTj_2132_creditrule", "path": "/", "secure": false, "value": "%E6%AF%8F%E5%A4%A9%E7%99%BB%E5%BD%95"}, {"domain": "www.seacms.net", "expiry": 1522165620.233811, "httpOnly": false, "name": "DbTj_2132_lastact", "path": "/", "secure": false, "value": "1522079220%09home.php%09spacecp"}, {"domain": "www.seacms.net", "expiry": 1522079250.234035, "httpOnly": false, "name": "DbTj_2132_checkpm", "path": "/", "secure": false, "value": "1"}, {"domain": "www.seacms.net", "expiry": 1553615220, "httpOnly": false, "name": "_fmdata", "path": "/", "secure": false, "value": "ku%2BFQZqzlbaJBIZeC0ha821U6iOLWyVpHEzxXyBis28FDqTqhHA3PW0xyQzFHWw4wg5y%2FbdaoztGGKFSjF7rF8o%2FaH%2FUhMIgARGKWOjAuGY%3D"}]