[{"domain": "www.hzsn.info", "httpOnly": false, "name": "Z85s_2132_creditnotice", "path": "/", "secure": false, "value": "0D0D2D0D0D0D0D0D0D31218"}, {"domain": "www.hzsn.info", "expiry": 1521997083, "httpOnly": false, "name": "cck_lasttime", "path": "/", "secure": false, "value": "1521903771699"}, {"domain": "www.hzsn.info", "expiry": 1524495759.226823, "httpOnly": false, "name": "Z85s_2132_lastvisit", "path": "/", "secure": false, "value": "1521900155"}, {"domain": "www.hzsn.info", "expiry": 1521904072.143443, "httpOnly": false, "name": "Z85s_2132_sendmail", "path": "/", "secure": false, "value": "1"}, {"domain": "www.hzsn.info", "expiry": 1524495759.226684, "httpOnly": true, "name": "Z85s_2132_saltkey", "path": "/", "secure": false, "value": "c5h0O55q"}, {"domain": "www.hzsn.info", "expiry": 1521990220.030317, "httpOnly": false, "name": "Z85s_2132_sid", "path": "/", "secure": false, "value": "UYo6yj"}, {"domain": "www.hzsn.info", "httpOnly": true, "name": "Z85s_2132_auth", "path": "/", "secure": false, "value": "5c42tOm0JI6yb7D4gpgOB2LltPRle45vZcx8gSEQ2Mye%2BrgAA6jRfBIicBTVKizObmKDKHBYcq3LXd0q8piLgwe1Lw"}, {"domain": "www.hzsn.info", "expiry": 1521997083, "httpOnly": false, "name": "cck_count", "path": "/", "secure": false, "value": "0"}, {"domain": "www.hzsn.info", "expiry": 1521904423, "httpOnly": false, "name": "Z85s_2132_noticeTitle", "path": "/", "secure": false, "value": "1"}, {"domain": "www.hzsn.info", "expiry": 1553439813.285976, "httpOnly": false, "name": "Z85s_2132_ulastactivity", "path": "/", "secure": false, "value": "1b0cTiq7Kwr0a6oSz5YskuHoe3JAnGyfnx7TDteP8sxa2ep2fly%2B"}, {"domain": "www.hzsn.info", "httpOnly": false, "name": "Z85s_2132_creditbase", "path": "/", "secure": false, "value": "0D0D0D0D0D0D0D0D0"}, {"domain": "www.hzsn.info", "httpOnly": false, "name": "Z85s_2132_creditrule", "path": "/", "secure": false, "value": "%E6%AF%8F%E5%A4%A9%E7%99%BB%E5%BD%95"}, {"domain": "www.hzsn.info", "expiry": 1521947020.029953, "httpOnly": false, "name": "Z85s_2132_security_cookiereport", "path": "/", "secure": false, "value": "53104mayof%2BeQrHKPAKrOJ1zijZvFivDo1wgJeYAHbDt%2FVa1aTL2"}, {"domain": "www.hzsn.info", "expiry": 1553439820.030114, "httpOnly": false, "name": "Z85s_2132_nofavfid", "path": "/", "secure": false, "value": "1"}, {"domain": "www.hzsn.info", "expiry": 1521903853.50845, "httpOnly": false, "name": "Z85s_2132_checkpm", "path": "/", "secure": false, "value": "1"}, {"domain": "www.hzsn.info", "expiry": 1553439823.510122, "httpOnly": false, "name": "Z85s_2132_lastcheckfeed", "path": "/", "secure": false, "value": "31218%7C1521903819"}, {"domain": "www.hzsn.info", "expiry": 1521903853.51036, "httpOnly": false, "name": "Z85s_2132_checkfollow", "path": "/", "secure": false, "value": "1"}, {"domain": "www.hzsn.info", "expiry": 1521990223.265226, "httpOnly": false, "name": "Z85s_2132_lastact", "path": "/", "secure": false, "value": "1521903820%09plugin.php%09"}]