[{"domain": "www.ynx1.com", "expiry": 1523766808.051243, "httpOnly": false, "name": "lck0_2132_sendmail", "path": "/", "secure": false, "value": "1"}, {"domain": ".ynx1.com", "expiry": 1523766569, "httpOnly": false, "name": "_gat_gtag_UA_111792927_1", "path": "/", "secure": false, "value": "1"}, {"domain": "www.ynx1.com", "expiry": 1523766564.978904, "httpOnly": false, "name": "lck0_2132_checkpm", "path": "/", "secure": false, "value": "1"}, {"domain": "www.ynx1.com", "httpOnly": false, "name": "__51cke__", "path": "/", "secure": false, "value": ""}, {"domain": "www.ynx1.com", "expiry": 1526358506.229468, "httpOnly": false, "name": "lck0_2132_lastvisit", "path": "/", "secure": false, "value": "1523763008"}, {"domain": "www.ynx1.com", "httpOnly": false, "name": "lck0_2132_creditnotice", "path": "/", "secure": false, "value": "0D0D10D0D0D0D0D0D0D20240"}, {"domain": "www.ynx1.com", "expiry": 1526358506.229357, "httpOnly": true, "name": "lck0_2132_saltkey", "path": "/", "secure": false, "value": "gyrrWJ9z"}, {"domain": "www.ynx1.com", "expiry": 1523852963.761752, "httpOnly": false, "name": "lck0_2132_lastact", "path": "/", "secure": false, "value": "1523766666%09misc.php%09patch"}, {"domain": "www.ynx1.com", "httpOnly": true, "name": "lck0_2132_auth", "path": "/", "secure": false, "value": "07cawyVJ2vS5A7baZuNxvbaUeIeDmEAuMtxdhHrOwgdyF2kk3cRNkuSvCKVcoUJ2WkkoSLdNMsVDrPjdvUFObxr9tQ"}, {"domain": ".ynx1.com", "expiry": 1523852963, "httpOnly": false, "name": "_gid", "path": "/", "secure": false, "value": "GA1.2.1194645427.1523766509"}, {"domain": ".ynx1.com", "expiry": 1586838563, "httpOnly": false, "name": "_ga", "path": "/", "secure": false, "value": "GA1.2.149068093.1523766509"}, {"domain": "www.ynx1.com", "expiry": 1523767163, "httpOnly": false, "name": "lck0_2132_noticeTitle", "path": "/", "secure": false, "value": "1"}, {"domain": "www.ynx1.com", "expiry": 1555302531.025497, "httpOnly": false, "name": "lck0_2132_ulastactivity", "path": "/", "secure": false, "value": "1f3beIDyekXbV4kZ8oediepHF102g8X2rHeKiM%2FSOAF%2B5grADtbw"}, {"domain": "www.ynx1.com", "httpOnly": false, "name": "lck0_2132_creditbase", "path": "/", "secure": false, "value": "0D0D0D0D0D0D0D0D0"}, {"domain": "www.ynx1.com", "httpOnly": false, "name": "lck0_2132_creditrule", "path": "/", "secure": false, "value": "%E6%AF%8F%E5%A4%A9%E7%99%BB%E5%BD%95"}, {"domain": "www.ynx1.com", "expiry": 1555302534.979871, "httpOnly": false, "name": "lck0_2132_lastcheckfeed", "path": "/", "secure": false, "value": "20240%7C1523766637"}, {"domain": "www.ynx1.com", "expiry": 1523766564.979984, "httpOnly": false, "name": "lck0_2132_checkfollow", "path": "/", "secure": false, "value": "1"}, {"domain": "www.ynx1.com", "expiry": 1523852963.091451, "httpOnly": false, "name": "lck0_2132_sid", "path": "/", "secure": false, "value": "oj24Fl"}, {"domain": "www.ynx1.com", "httpOnly": false, "name": "lck0_2132_lip", "path": "/", "secure": false, "value": "113.68.179.87%2C1523766637"}, {"domain": "www.ynx1.com", "httpOnly": false, "name": "__51laig__", "path": "/", "secure": false, "value": "2"}, {"domain": "www.ynx1.com", "httpOnly": false, "name": "__tins__19354760", "path": "/", "secure": false, "value": "%7B%22sid%22%3A%201523766508258%2C%20%22vd%22%3A%202%2C%20%22expires%22%3A%201523768363492%7D"}]