[{"domain": "woaipuyou.com", "expiry": 1524497217.975588, "httpOnly": true, "name": "OjaV_2132_saltkey", "path": "/", "secure": false, "value": "f4BTbpG3"}, {"domain": "woaipuyou.com", "expiry": 1521948580.622396, "httpOnly": false, "name": "OjaV_2132_security_cookiereport", "path": "/", "secure": false, "value": "a711of5AW20E59hsoFZhRaU3xp26yOsTV%2FZmwhdtw3SscQ7VIFgd"}, {"domain": "woaipuyou.com", "expiry": 1521905518.928775, "httpOnly": false, "name": "OjaV_2132_sendmail", "path": "/", "secure": false, "value": "1"}, {"domain": "woaipuyou.com", "expiry": 1521905421.720451, "httpOnly": false, "name": "OjaV_2132_checkpm", "path": "/", "secure": false, "value": "1"}, {"domain": "woaipuyou.com", "expiry": 1524497217.975733, "httpOnly": false, "name": "OjaV_2132_lastvisit", "path": "/", "secure": false, "value": "1521901615"}, {"domain": "woaipuyou.com", "httpOnly": true, "name": "OjaV_2132_auth", "path": "/", "secure": false, "value": "e7a6jcPzo8xO8M88zMVRy3XAiU3jlp5bs6tf3YO517tpR1GLhjUUyrywTlYxpxgv1bJtxqFpnMUgQOz8uO9ha3ObXg"}, {"domain": "woaipuyou.com", "httpOnly": false, "name": "OjaV_2132_seccode", "path": "/", "secure": false, "value": "14897.961168e68b85e22635"}, {"domain": "woaipuyou.com", "expiry": 1521991780.622493, "httpOnly": false, "name": "OjaV_2132_sid", "path": "/", "secure": false, "value": "y909z9"}, {"domain": "woaipuyou.com", "expiry": 1521905680.622464, "httpOnly": false, "name": "OjaV_2132_onlineusernum", "path": "/", "secure": false, "value": "132"}, {"domain": "woaipuyou.com", "httpOnly": false, "name": "OjaV_2132_secqaa", "path": "/", "secure": false, "value": "14898.650daf25456a6c4bbf"}, {"domain": "woaipuyou.com", "expiry": 1553441376.796596, "httpOnly": false, "name": "OjaV_2132_ulastactivity", "path": "/", "secure": false, "value": "318aYHWOAQttpiP0jJJ1kjXWr2PGKGZYk6yLxzkRjTklUc6aUaYj"}, {"domain": "woaipuyou.com", "expiry": 1553441380.62243, "httpOnly": false, "name": "OjaV_2132_nofavfid", "path": "/", "secure": false, "value": "1"}, {"domain": "woaipuyou.com", "expiry": 1521991791.720341, "httpOnly": false, "name": "OjaV_2132_lastact", "path": "/", "secure": false, "value": "1521905389%09home.php%09spacecp"}, {"domain": "woaipuyou.com", "expiry": 1521905991, "httpOnly": false, "name": "OjaV_2132_noticeTitle", "path": "/", "secure": false, "value": "1"}]